test_pypi_kmaddela/__init__.py
test_pypi_kmaddela/hello.py
test_pypi_kmaddela-0.4.17.dist-info/METADATA
test_pypi_kmaddela-0.4.17.dist-info/WHEEL
test_pypi_kmaddela-0.4.17.dist-info/RECORD
